pytest_fixture_remover/__init__.py
pytest_fixture_remover/codemod.py
pytest_fixture_remover-1.0.1.post1.dist-info/LICENSE
pytest_fixture_remover-1.0.1.post1.dist-info/METADATA
pytest_fixture_remover-1.0.1.post1.dist-info/WHEEL
pytest_fixture_remover-1.0.1.post1.dist-info/RECORD
