Metadata-Version: 2.1
Name: pytest-fixture-remover
Version: 1.0.1.post1
Summary: A LibCST codemod to remove pytest fixtures applied via the usefixtures decorator, as well as its parametrizations.
Home-page: https://github.com/Klavionik/pytest-fixture-remover
Author: Roman Vlasenko
Author-email: klavionik@gmail.com
Requires-Python: >=3.8,<4.0
Classifier: Development Status :: 5 - Production/Stable
Classifier: Framework :: Pytest
Classifier: Intended Audience :: Developers
Classifier: Programming Language :: Python :: 3
Classifier: Programming Language :: Python :: 3.8
Classifier: Programming Language :: Python :: 3.9
Classifier: Programming Language :: Python :: 3.10
Classifier: Programming Language :: Python :: 3.11
Classifier: Programming Language :: Python :: 3.12
Requires-Dist: libcst (>=1.1.0,<2.0.0)
